{"3bbedc00-997a-4859-899c-92c6288a44ae":{"serviceName":"test","description":"test","IP":"127.0.0.1","localNetwork":true,"hasWebUI":true,"canRemoteAccess":true,"webUI":"test","serviceStatus":"Unknown"},"84121709-2702-42e4-8609-8043369337b7":{"serviceName":"test2s sdfsdfsdfsdf sdfsdfsdfsd f","description":"test2 sdfsdfsdf sdf sdf sdf sdf sdf sdf sdf sd fsdf sdfsdf sdfsdfsdfsdfsdfsdf sdf s df","IP":"127.0.0.1","localNetwork":false,"hasWebUI":false,"canRemoteAccess":true,"webUI":"test","serviceStatus":"Unknown"},"028253c0-6876-44fa-bd11-9f0d288857cb":{"serviceName":"teset","description":"test","IP":"test","localNetwork":true,"hasWebUI":true,"canRemoteAccess":true,"webUI":"tesdfsdfe3sdfswef","serviceStatus":"Unknown"},"5089c5ed-4fbd-46fa-a715-5965e663c866":{"serviceName":"test","description":"test","IP":"127.0.0.1","localNetwork":true,"hasWebUI":true,"canRemoteAccess":true,"webUI":"test","serviceStatus":"Unknown"}}